pymupdf4llm_c/models.py
pymupdf4llm_c/__init__.py
pymupdf4llm_c/api.py
pymupdf4llm_c/_cffi.py
pymupdf4llm_c/main.py
pymupdf4llm_c/_block_converter.py
pymupdf4llm_c/.dylibs/libcrypto.3.dylib
pymupdf4llm_c/.dylibs/libmupdf.dylib
pymupdf4llm_c/lib/libtomd.dylib
pymupdf4llm_c-2.0.0.dist-info/RECORD
pymupdf4llm_c-2.0.0.dist-info/WHEEL
pymupdf4llm_c-2.0.0.dist-info/entry_points.txt
pymupdf4llm_c-2.0.0.dist-info/top_level.txt
pymupdf4llm_c-2.0.0.dist-info/METADATA
pymupdf4llm_c-2.0.0.dist-info/licenses/LICENSE
