Metadata-Version: 2.4
Name: pymupdf4llm-c
Version: 2.0.0
Summary: C-backed PDF to structured JSON extractor.
Author: Adit Bajaj
License-Expression: AGPL-3.0
Project-URL: Homepage, https://github.com/intercepted16/pymupdf4llm-C
Project-URL: Repository, https://github.com/intercepted16/pymupdf4llm-C
Project-URL: Issues, https://github.com/intercepted16/pymupdf4llm-C/issues
Requires-Python: >=3.9
License-File: LICENSE
Requires-Dist: cffi
Requires-Dist: pydantic
Provides-Extra: dev
Requires-Dist: ruff; extra == "dev"
Requires-Dist: build; extra == "dev"
Dynamic: license-file
